speedlimit/__init__.py
speedlimit-0.1.1.dist-info/WHEEL
speedlimit-0.1.1.dist-info/pbr.json
speedlimit-0.1.1.dist-info/metadata.json
speedlimit-0.1.1.dist-info/RECORD
speedlimit-0.1.1.dist-info/DESCRIPTION.rst
speedlimit-0.1.1.dist-info/METADATA
speedlimit-0.1.1.dist-info/top_level.txt
